BMI_rule/your_BMI.py
BMI_rule-0.0.0.3.dist-info/METADATA
BMI_rule-0.0.0.3.dist-info/WHEEL
BMI_rule-0.0.0.3.dist-info/top_level.txt
BMI_rule-0.0.0.3.dist-info/RECORD
