Metadata-Version: 2.1
Name: BMI-rule
Version: 0.0.0.3
Summary: BMI calculate, Height : cm, Weight : kg.
Home-page: UNKNOWN
Author: rule_manu
Author-email: kdl0068@naver.com
License: MIT
Platform: UNKNOWN
Requires-Python: >=3
